{"cameraMode":{"drawMode":0,"name":"Shaded","section":"Shading Mode"},"sceneLighting":true,"audioPlay":false,"sceneViewState":{"showFog":true,"showMaterialUpdate":false,"showSkybox":true,"showFlares":true,"showImageEffects":true,"showParticleSystems":true},"in2DMode":false,"pivot":{"x":22.073711395263673,"y":1.1827774047851563,"z":10.160476684570313},"rotation":{"x":-0.3665744662284851,"y":0.15986333787441255,"z":-0.0640949234366417,"w":-0.9143078327178955},"size":135.5139617919922,"orthographic":false}